cursolfiap/__init__.py
cursolfiap/core.py
cursolfiap_package-1.0.0.dist-info/METADATA
cursolfiap_package-1.0.0.dist-info/WHEEL
cursolfiap_package-1.0.0.dist-info/top_level.txt
cursolfiap_package-1.0.0.dist-info/RECORD
