Metadata-Version: 2.4
Name: cursolfiap-package
Version: 1.0.0
Summary: Minha Primeira Lib Curso FIAP
Home-page: https://github.com/bwasistemas/fiap
Author: Bruno Amorim
Author-email: rm365279@fiap.com.br
License: MIT
Dynamic: author
Dynamic: author-email
Dynamic: description
Dynamic: description-content-type
Dynamic: home-page
Dynamic: license
Dynamic: summary
